<?xml version="1.0" encoding="UTF-8" standalone="yes"?>
<addon id="plugin.service.carpcButler" name="CarPC Butler" version="0.0.0" provider-name="Peziman">
  <requires>
    <import addon="xbmc.python" version="2.1.0"/>
  </requires>
  <extension point="xbmc.service" library="service.py" start="login" />
  <extension point="xbmc.addon.metadata">
    <platform>linux</platform>
    <description lang="en">Some automatic stuff for carpc</description>
    <license>GNU GENERAL PUBLIC LICENSE. Version 2, June 1991</license>
    <language></language>
    <forum>www.raspicarprojekte.de</forum>
  </extension>
</addon>
